FinanceScraper-0.2.1.data/scripts/example.py
FinanceScraper-0.2.1.data/scripts/full_example.py
financescraper/__init__.py
financescraper/core/__init__.py
financescraper/core/conversions.py
financescraper/core/scraper.py
financescraper/datacontainer/__init__.py
financescraper/datacontainer/circular_buffer.py
financescraper/datacontainer/container.py
financescraper/util/__init__.py
financescraper/util/circular_buffer.py
financescraper/util/conversions.py
FinanceScraper-0.2.1.dist-info/LICENSE
FinanceScraper-0.2.1.dist-info/METADATA
FinanceScraper-0.2.1.dist-info/WHEEL
FinanceScraper-0.2.1.dist-info/top_level.txt
FinanceScraper-0.2.1.dist-info/RECORD
