Metadata-Version: 2.1
Name: FinanceScraper
Version: 0.2.1
Summary: An up-to-date web scraper providing financial data from various sources
Home-page: https://github.com/LukasBudach/FinanceScraper
Author: Lukas Budach
Author-email: lukas.budach@student.hpi.de
License: UNKNOWN
Platform: UNKNOWN
Classifier: Programming Language :: Python :: 3
Classifier: License :: OSI Approved :: MIT License
Classifier: Operating System :: OS Independent
Requires-Dist: requests
